{"version":2,"version_hash":"8asa4K+9toCin27pl7eh21KOPkwZkbu3/UJbZnVmYho=","engine_version":11,"name":"transactions","tables":{"_dlt_version":{"name":"_dlt_version","columns":{"version":{"name":"version","data_type":"bigint","nullable":false},"engine_version":{"name":"engine_version","data_type":"bigint","nullable":false},"inserted_at":{"name":"inserted_at","data_type":"timestamp","nullable":false},"schema_name":{"name":"schema_name","data_type":"text","nullable":false},"version_hash":{"name":"version_hash","data_type":"text","nullable":false},"schema":{"name":"schema","data_type":"text","nullable":false}},"write_disposition":"skip","resource":"_dlt_version","description":"Created by DLT. Tracks schema updates"},"_dlt_loads":{"name":"_dlt_loads","columns":{"load_id":{"name":"load_id","data_type":"text","nullable":false,"precision":64},"schema_name":{"name":"schema_name","data_type":"text","nullable":true},"status":{"name":"status","data_type":"bigint","nullable":false},"inserted_at":{"name":"inserted_at","data_type":"timestamp","nullable":false},"schema_version_hash":{"name":"schema_version_hash","data_type":"text","nullable":true}},"write_disposition":"skip","resource":"_dlt_loads","description":"Created by DLT. Tracks completed loads"},"transaction":{"columns":{"id":{"name":"id","nullable":false,"primary_key":true,"data_type":"text"},"transaction_id":{"name":"transaction_id","data_type":"text","nullable":true},"customer_id":{"name":"customer_id","data_type":"text","nullable":true},"amount":{"name":"amount","data_type":"double","nullable":true},"currency":{"name":"currency","data_type":"text","nullable":true},"event_time":{"name":"event_time","data_type":"timestamp","nullable":true},"transaction_status":{"name":"transaction_status","data_type":"text","nullable":true},"category":{"name":"category","data_type":"text","nullable":true},"metadata__source":{"name":"metadata__source","data_type":"text","nullable":true},"metadata__extracted_at":{"name":"metadata__extracted_at","data_type":"timestamp","nullable":true},"metadata__is_late_arrival":{"name":"metadata__is_late_arrival","data_type":"bool","nullable":true},"_dlt_load_id":{"name":"_dlt_load_id","data_type":"text","nullable":false},"_dlt_id":{"name":"_dlt_id","data_type":"text","nullable":false,"unique":true,"row_key":true}},"write_disposition":"merge","name":"transaction","resource":"transaction","x-normalizer":{"seen-data":true}},"_dlt_pipeline_state":{"columns":{"version":{"name":"version","data_type":"bigint","nullable":false},"engine_version":{"name":"engine_version","data_type":"bigint","nullable":false},"pipeline_name":{"name":"pipeline_name","data_type":"text","nullable":false},"state":{"name":"state","data_type":"text","nullable":false},"created_at":{"name":"created_at","data_type":"timestamp","nullable":false},"version_hash":{"name":"version_hash","data_type":"text","nullable":true},"_dlt_load_id":{"name":"_dlt_load_id","data_type":"text","nullable":false,"precision":64},"_dlt_id":{"name":"_dlt_id","data_type":"text","nullable":false,"unique":true,"row_key":true}},"write_disposition":"append","file_format":"preferred","name":"_dlt_pipeline_state","resource":"_dlt_pipeline_state","x-normalizer":{"seen-data":true}}},"settings":{"detections":["iso_timestamp"],"default_hints":{"not_null":["_dlt_id","_dlt_root_id","_dlt_parent_id","_dlt_list_idx","_dlt_load_id"],"parent_key":["_dlt_parent_id"],"root_key":["_dlt_root_id"],"unique":["_dlt_id"],"row_key":["_dlt_id"]}},"normalizers":{"names":"snake_case","json":{"module":"dlt.common.normalizers.json.relational","config":{"propagation":{"tables":{"transaction":{"_dlt_id":"_dlt_root_id"}}}}}},"previous_hashes":["MBJ3ILfRmJuh7bZiyAN7FryCJDxskArEU6s08ou6XNM=","vtpZU1nHwGMS99pOhPz/eC2bCbbzSkaTnBIoEXtapzA="]}